country/__init__.py
country/admin.py
country/apps.py
country/models.py
country/tests.py
country/views.py
country/migrations/0001_initial.py
country/migrations/__init__.py
currency/__init__.py
currency/admin.py
currency/apps.py
currency/models.py
currency/tests.py
currency/views.py
currency/migrations/0001_initial.py
currency/migrations/__init__.py
phonecode/__init__.py
phonecode/admin.py
phonecode/apps.py
phonecode/models.py
phonecode/tests.py
phonecode/utils.py
phonecode/views.py
phonecode/migrations/0001_initial.py
phonecode/migrations/__init__.py
django_country_utils-0.2.0.dist-info/LICENSE
django_country_utils-0.2.0.dist-info/METADATA
django_country_utils-0.2.0.dist-info/WHEEL
django_country_utils-0.2.0.dist-info/top_level.txt
django_country_utils-0.2.0.dist-info/RECORD
